{
    "emailregst" : "handler@yahoo.co.id",

    "passwordregst" : "Mozaa89",

    "uniqepass1" : "peanuts88",

    "uniqepass2" : "Peanuts",

    "uniqepass3" : "PEANUTS88",

    "emailfix" : "lf.loidforger@gmail.com",

    "passwordfix" : "Anyaforger99",

    "passwordfalse" : "Damiandesmond12",

    "emailun" : "forger@gmail.co.id",

    "first1" : "Yor",

    "first2" : "Loid",

    "label1" : "Rumah 2",

    "name" : "Loid",

    "pNumber" : "082233457890",
    
    "postal1" : "12430",

    "detail1" : "7, Jl. TB Simatupang No.18C, RT.7/RW.9, West Cilandak, Cilandak, South Jakarta City, Jakarta 12430",

    "note1" : "The CEO Building (Cilandak Executive Office)",

    "label2" : "Rumah 2",
    
    "detail2" : "Green Lake City Ruko Food City No.22, Duri Kosambi, Kecamatan Cengkareng, Kota Jakarta Barat.",

    "note2" : "MAISON TATEI - Green Lake City"

}